GeAI/__init__.py
GeAI/available_models.py
GeAI/connect.py
GeAI/txt/__init__.py
GeAI/txt/explain_code.py
GeAI/txt/fix_grammar.py
GeAI/txt/optimize_code.py
GeAI/utils/GeAI_utils.py
GeAI/utils/__init__.py
GeAI-0.1.7.dist-info/METADATA
GeAI-0.1.7.dist-info/WHEEL
GeAI-0.1.7.dist-info/top_level.txt
GeAI-0.1.7.dist-info/RECORD
