Metadata-Version: 2.1
Name: GeAI
Version: 0.1.7
Summary: Generative Artificial Intelligence
Home-page: https://genai.gd.edu.kg/
Author: Li Yuan
Author-email: <lyuan@gd.edu.kg>
Keywords: Generative AI,LLM,API
Classifier: Development Status :: 3 - Alpha
Classifier: Intended Audience :: Education
Classifier: Programming Language :: Python :: 3
Classifier: Operating System :: MacOS :: MacOS X
Classifier: Operating System :: Microsoft :: Windows
